dbrownell_CommitEmojis/Lib.py
dbrownell_CommitEmojis/MainApp.py
dbrownell_CommitEmojis/MainApp.tcss
dbrownell_CommitEmojis/__init__.py
dbrownell_CommitEmojis/__main__.py
dbrownell_CommitEmojis/catagories.json
dbrownell_CommitEmojis/gitmojis.json
dbrownell_CommitEmojis/py.typed
dbrownell_CommitEmojis/schema.json
dbrownell_commitemojis-0.2.0.dist-info/WHEEL
dbrownell_commitemojis-0.2.0.dist-info/entry_points.txt
dbrownell_commitemojis-0.2.0.dist-info/METADATA
dbrownell_commitemojis-0.2.0.dist-info/RECORD
