Metadata-Version: 2.3
Name: dbrownell-commitemojis
Version: 0.2.0
Summary: Tools that enhance the gitmoji (https://gitmoji.dev/) experience.
Author: David Brownell
Author-email: David Brownell <github@DavidBrownell.com>
License: MIT
Classifier: Operating System :: MacOS
Classifier: Operating System :: Microsoft :: Windows
Classifier: Operating System :: POSIX :: Linux
Classifier: Programming Language :: Python
Classifier: Programming Language :: Python :: 3.14
Classifier: Programming Language :: Python :: 3.13
Classifier: Programming Language :: Python :: 3.12
Classifier: Programming Language :: Python :: 3.11
Classifier: Programming Language :: Python :: 3.10
Requires-Dist: dbrownell-common>=0.16.0
Requires-Dist: pyperclip>=1.11.0
Requires-Dist: rich>=14.1.0
Requires-Dist: textual>=6.1.0
Requires-Dist: typer>=0.19.2
Requires-Python: >=3.10
Project-URL: Documentation, https://github.com/davidbrownell/dbrownell_CommitEmojis
Project-URL: Homepage, https://github.com/davidbrownell/dbrownell_CommitEmojis
Project-URL: Repository, https://github.com/davidbrownell/dbrownell_CommitEmojis
